chartspan/__init__.py
chartspan/chartspan.py
tests/__init__.py
tests/test_chartspan.py
chartspan-0.1.2.dist-info/METADATA
chartspan-0.1.2.dist-info/WHEEL
chartspan-0.1.2.dist-info/top_level.txt
chartspan-0.1.2.dist-info/RECORD
