Metadata-Version: 2.2
Name: chartspan
Version: 0.1.2
Summary: A lightweight Python library for rendering Vega-Lite JSON charts in Jupyter/Colab.
Author-email: David Jeremiah <flasconnect@gmail.com>
Project-URL: Homepage, https://github.com/davidkjeremiah/chartspan
Project-URL: Issues, https://github.com/davidkjeremiah/chartspan
Classifier: Programming Language :: Python :: 3
Classifier: License :: OSI Approved :: MIT License
Classifier: Operating System :: OS Independent
Requires-Python: >=3.6
Requires-Dist: IPython>=7.0
